wpcsys/__init__.py
wpcsys/libusb-1.0.dll
wpcsys/pywpc.cp310-win_amd64.pyd
wpcsys/pywpc.cp311-win_amd64.pyd
wpcsys/pywpc.cp312-win_amd64.pyd
wpcsys/pywpc.cp38-win_amd64.pyd
wpcsys/pywpc.cp39-win_amd64.pyd
wpcsys/version.py
wpcsys-3.2.0.dist-info/LICENSE
wpcsys-3.2.0.dist-info/METADATA
wpcsys-3.2.0.dist-info/WHEEL
wpcsys-3.2.0.dist-info/top_level.txt
wpcsys-3.2.0.dist-info/RECORD
