Metadata-Version: 2.1
Name: wpcsys
Version: 3.2.0
Summary: WPC Python driver APIs, the easiest way to Control & Data Acquisition (DAQ)
Home-page: https://github.com/WPC-Systems-Ltd/WPC_Python_driver_release
Author: Chunglee people, Chieh-An Lin
Author-email: wu@wpc.com.tw
License: MIT
Keywords: WPC,DAQ,Motion card,Motion driver,USB,Ethernet,Wifi
Classifier: Development Status :: 5 - Production/Stable
Classifier: Intended Audience :: Science/Research
Classifier: Intended Audience :: Developers
Classifier: Operating System :: Microsoft :: Windows :: Windows 10
Classifier: Programming Language :: Python :: 3.8
Classifier: Programming Language :: Python :: 3.9
Classifier: Programming Language :: Python :: 3.10
Classifier: Topic :: Software Development :: Embedded Systems
Classifier: Topic :: System :: Hardware :: Hardware Drivers
Classifier: Topic :: Documentation :: Sphinx
Classifier: Topic :: Software Development :: Libraries :: Python Modules
Requires-Python: >=3.8
License-File: LICENSE
Requires-Dist: pyusb (>=1.2.1)
Requires-Dist: numpy (>=1.23.0)
Requires-Dist: qasync (>=0.23.0)
Requires-Dist: matplotlib (>=3.5.2)
Requires-Dist: PyQt5 (>=5.15.4)
Requires-Dist: PyQt5-Qt5 (>=5.15.2)
Requires-Dist: PyQt5-sip (>=12.10.1)
Requires-Dist: wpcEXEbuild (>=0.0.1)
